cjm_diffusers_utils/__init__.py
cjm_diffusers_utils/_modidx.py
cjm_diffusers_utils/core.py
cjm_diffusers_utils/diffusers_utils.py
cjm_diffusers_utils-0.0.3.dist-info/LICENSE
cjm_diffusers_utils-0.0.3.dist-info/METADATA
cjm_diffusers_utils-0.0.3.dist-info/WHEEL
cjm_diffusers_utils-0.0.3.dist-info/entry_points.txt
cjm_diffusers_utils-0.0.3.dist-info/top_level.txt
cjm_diffusers_utils-0.0.3.dist-info/RECORD
