Metadata-Version: 2.1
Name: cjm-diffusers-utils
Version: 0.0.3
Summary: Some utility functions I frequently use with 🤗 diffusers.
Home-page: https://github.com/cj-mills/cjm-diffusers-utils
Author: cj-mills
Author-email: millscj.mills2@gmail.com
License: Apache Software License 2.0
Keywords: nbdev jupyter notebook python
Classifier: Development Status :: 4 - Beta
Classifier: Intended Audience :: Developers
Classifier: Natural Language :: English
Classifier: Programming Language :: Python :: 3.7
Classifier: Programming Language :: Python :: 3.8
Classifier: Programming Language :: Python :: 3.9
Classifier: Programming Language :: Python :: 3.10
Classifier: License :: OSI Approved :: Apache Software License
Requires-Python: >=3.7
License-File: LICENSE
Requires-Dist: fastcore
Requires-Dist: tqdm
Requires-Dist: torch
Requires-Dist: torchvision
Requires-Dist: diffusers
Requires-Dist: transformers
Requires-Dist: accelerate
Requires-Dist: cjm-pytorch-utils
Provides-Extra: dev
